ssdeep-stubs/__about__.pyi
ssdeep-stubs/__init__.pyi
ssdeep-stubs/_build.pyi
ssdeep_stubs-0.0.1.dist-info/LICENSE
ssdeep_stubs-0.0.1.dist-info/METADATA
ssdeep_stubs-0.0.1.dist-info/WHEEL
ssdeep_stubs-0.0.1.dist-info/top_level.txt
ssdeep_stubs-0.0.1.dist-info/RECORD
