Metadata-Version: 2.1
Name: ssdeep-stubs
Version: 0.0.1
Summary: python-ssdeep stubs and mypy plugin
Home-page: https://github.com/thavelick/python-ssdeep-stubs
Author: Tristan Havelick
Author-email: tristan@havelick.com
License: GPL
Platform: UNKNOWN
Classifier: Development Status :: 3 - Alpha
Classifier: Programming Language :: Python :: 3
License-File: LICENSE
Requires-Dist: mypy
